py_canonicalizer/canonicalizer.py
py_canonicalizer-0.1.0.dist-info/METADATA
py_canonicalizer-0.1.0.dist-info/WHEEL
py_canonicalizer-0.1.0.dist-info/top_level.txt
py_canonicalizer-0.1.0.dist-info/RECORD
