Metadata-Version: 2.4
Name: py-canonicalizer
Version: 0.1.0
Summary: A universal tool for preparing polyline data for algorithms like RDP, by solving the arbitrary start-point problem.
Author-email: Your Name <your_email@example.com>
Keywords: rdp-algorithm,polyline-simplification,canonical,computational-geometry,gis,rhino,grasshopper
Classifier: Development Status :: 3 - Alpha
Classifier: Intended Audience :: Developers
Classifier: Intended Audience :: Education
Classifier: Intended Audience :: Science/Research
Classifier: Programming Language :: Python :: 3
Classifier: Programming Language :: Python :: 3.8
Classifier: Programming Language :: Python :: 3.9
Classifier: Programming Language :: Python :: 3.10
Classifier: Programming Language :: Python :: 3.11
Classifier: Programming Language :: Python :: 3.12
Classifier: License :: OSI Approved :: MIT License
Classifier: Topic :: Scientific/Engineering
Classifier: Operating System :: OS Independent
Requires-Python: >=3.8
Requires-Dist: numpy
